text_emotion_detection/__init__.py
text_emotion_detection/main.py
text_emotion_detection/model.py
text_emotion_detection/preprocessing.py
text_emotion_detection/utils.py
text_emotion_description-0.3.dist-info/METADATA
text_emotion_description-0.3.dist-info/WHEEL
text_emotion_description-0.3.dist-info/entry_points.txt
text_emotion_description-0.3.dist-info/top_level.txt
text_emotion_description-0.3.dist-info/RECORD
