Metadata-Version: 2.1
Name: text_emotion_description
Version: 0.3
Summary: A Python package for emotion detection using neural networks
Author: Ankith Manchale
Classifier: Programming Language :: Python :: 3
Classifier: Operating System :: OS Independent
Requires-Python: >=3.6
Requires-Dist: pandas
Requires-Dist: numpy
Requires-Dist: seaborn
Requires-Dist: matplotlib
Requires-Dist: nltk
Requires-Dist: scikit-learn
Requires-Dist: tensorflow
Requires-Dist: keras
